{
    "tool_id": "concrete-footing-volume-calculator",
    "tool_category": "concrete",
    "intent_type": "calculate",
    "tool_name": "Concrete Footing Volume Calculator",
    "tool_purpose": "Calculates the concrete volume required for a continuous rectangular footing.",
    "inputs": [
        {
            "input_id": "footing_length",
            "label": "Footing Length",
            "type": "number",
            "unit": "feet",
            "constraints": {
                "min": 0.1,
                "required": true
            },
            "default_value": 40,
            "explanation": "The total length of the footing trench."
        },
        {
            "input_id": "footing_width",
            "label": "Footing Width",
            "type": "number",
            "unit": "inches",
            "constraints": {
                "min": 6,
                "required": true
            },
            "default_value": 16,
            "explanation": "The width of the footing trench."
        },
        {
            "input_id": "footing_depth",
            "label": "Footing Depth",
            "type": "number",
            "unit": "inches",
            "constraints": {
                "min": 6,
                "required": true
            },
            "default_value": 8,
            "explanation": "The depth (thickness) of the concrete footing."
        }
    ],
    "calculation_logic": {
        "variables": {
            "length_ft": "footing_length",
            "width_ft": "footing_width / 12",
            "depth_ft": "footing_depth / 12"
        },
        "formula": "length_ft * width_ft * depth_ft",
        "rounding": {
            "decimals": 2,
            "method": "round"
        }
    },
    "outputs": [
        {
            "output_id": "volume_cubic_feet",
            "label": "Concrete Volume",
            "unit": "cubic feet",
            "description": "Total volume of concrete required for the footing in cubic feet."
        },
        {
            "output_id": "volume_cubic_yards",
            "label": "Concrete Volume",
            "unit": "cubic yards",
            "description": "Total volume of concrete required for the footing in cubic yards."
        }
    ],
    "assumptions": [
        "The footing is continuous and rectangular.",
        "Dimensions are uniform.",
        "No waste or overage is included."
    ],
    "seo": {
        "title_template": "Concrete Footing Volume Calculator",
        "meta_description": "Calculate the concrete volume needed for continuous footings based on length, width, and depth."
    },
    "structured_data": {
        "applicationCategory": "ConstructionCalculator",
        "inputType": [
            "length",
            "width",
            "depth"
        ],
        "outputType": [
            "concreteVolume"
        ]
    },
    "tool_notes": [
        {
            "title": "How this calculator works",
            "text": "This calculator calculates concrete volume by multiplying footing length, width, and depth."
        },
        {
            "title": "When to use this calculator",
            "text": "Use this calculator for continuous concrete footings under walls, foundations, or structural supports."
        }
    ],
    "indexing": {
        "indexable": true
    },
    "monetization": {
        "ads_enabled": false
    },
    "distribution": {
        "parasites_enabled": true,
        "platforms": []
    }
}